{
    "100m": [
        {
            "place": 1,
            "athlete": {
                "text": "Martin, Jalena",
                "link": "https://www.tfrrs.org/athletes/8984291/Bryant/Jalena_Martin"
            },
            "team": null,
            "year": "FR-1",
            "time": "11.75",
            "meet_date": "May 10, 2025",
            "wind": "2.2"
        },
        {
            "place": 2,
            "athlete": {
                "text": "Kane, Marie",
                "link": "https://www.tfrrs.org/athletes/8984290/Bryant/Marie_Kane"
            },
            "team": null,
            "year": "FR-1",
            "time": "12.07",
            "meet_date": "May 10, 2025",
            "wind": "2.2"
        },
        {
            "place": 3,
            "athlete": {
                "text": "Braswell, Iyana",
                "link": "https://www.tfrrs.org/athletes/8675806/Bryant/Iyana_Braswell"
            },
            "team": null,
            "year": "SO-2",
            "time": "12.11",
            "meet_date": "May 10, 2025",
            "wind": "2.2"
        },
        {
            "place": 4,
            "athlete": {
                "text": "Collins, Jordyn",
                "link": "https://www.tfrrs.org/athletes/9090360/Bryant/Jordyn_Collins"
            },
            "team": null,
            "year": "SR-4",
            "time": "12.15",
            "meet_date": "May 10, 2025",
            "wind": "2.2"
        },
        {
            "place": 5,
            "athlete": {
                "text": "Pineda, Savannah",
                "link": "https://www.tfrrs.org/athletes/7981526/Bryant/Savannah_Pineda"
            },
            "team": null,
            "year": "SR-4",
            "time": "12.22",
            "meet_date": "Apr 12, 2025",
            "wind": "1.5"
        },
        {
            "place": 6,
            "athlete": {
                "text": "Haddad, Lauren",
                "link": "https://www.tfrrs.org/athletes/8675807/Bryant/Lauren_Haddad"
            },
            "team": null,
            "year": "SO-2",
            "time": "12.83",
            "meet_date": "Mar 14, 2025",
            "wind": "-0.2"
        },
        {
            "place": 7,
            "athlete": {
                "text": "Broussard, Amanda",
                "link": "https://www.tfrrs.org/athletes/8328693/Bryant/Amanda_Broussard"
            },
            "team": null,
            "year": "JR-3",
            "time": "12.84",
            "meet_date": "Mar 14, 2025",
            "wind": "-0.2"
        },
        {
            "place": 8,
            "athlete": {
                "text": "De La Rosa, Tishany",
                "link": "https://www.tfrrs.org/athletes/8984287/Bryant/Tishany_De_La_Rosa"
            },
            "team": null,
            "year": "FR-1",
            "time": "13.00",
            "meet_date": "Mar 14, 2025",
            "wind": "-0.2"
        },
        {
            "place": 9,
            "athlete": {
                "text": "Sanders, Sarina",
                "link": "https://www.tfrrs.org/athletes/8984292/Bryant/Sarina_Sanders"
            },
            "team": null,
            "year": "FR-1",
            "time": "13.11",
            "meet_date": "Mar 14, 2025",
            "wind": "-0.2"
        },
        {
            "place": 10,
            "athlete": {
                "text": "Marsella, Bethany",
                "link": "https://www.tfrrs.org/athletes/8675809/Bryant/Bethany_Marsella"
            },
            "team": null,
            "year": "SO-2",
            "time": "13.32",
            "meet_date": "Apr 18, 2025",
            "wind": "-1.2"
        }
    ],
    "200m": [
        {
            "place": 1,
            "athlete": {
                "text": "Pineda, Savannah",
                "link": "https://www.tfrrs.org/athletes/7981526/Bryant/Savannah_Pineda"
            },
            "team": null,
            "year": "SR-4",
            "time": "24.79",
            "meet_date": "Apr 3, 2025",
            "wind": "0.9"
        },
        {
            "place": 2,
            "athlete": {
                "text": "Collins, Jordyn",
                "link": "https://www.tfrrs.org/athletes/9090360/Bryant/Jordyn_Collins"
            },
            "team": null,
            "year": "SR-4",
            "time": "25.28",
            "meet_date": "May 3, 2025",
            "wind": "0.2"
        },
        {
            "place": 3,
            "athlete": {
                "text": "Haddad, Lauren",
                "link": "https://www.tfrrs.org/athletes/8675807/Bryant/Lauren_Haddad"
            },
            "team": null,
            "year": "SO-2",
            "time": "25.49",
            "meet_date": "May 16, 2025",
            "wind": "0.2"
        },
        {
            "place": 4,
            "athlete": {
                "text": "Broussard, Amanda",
                "link": "https://www.tfrrs.org/athletes/8328693/Bryant/Amanda_Broussard"
            },
            "team": null,
            "year": "JR-3",
            "time": "25.49",
            "meet_date": "May 16, 2025",
            "wind": "1.9"
        },
        {
            "place": 5,
            "athlete": {
                "text": "Kalinowski, Amanda",
                "link": "https://www.tfrrs.org/athletes/8984289/Bryant/Amanda_Kalinowski"
            },
            "team": null,
            "year": "FR-1",
            "time": "25.95",
            "meet_date": "May 3, 2025",
            "wind": "2.4"
        },
        {
            "place": 6,
            "athlete": {
                "text": "De La Rosa, Tishany",
                "link": "https://www.tfrrs.org/athletes/8984287/Bryant/Tishany_De_La_Rosa"
            },
            "team": null,
            "year": "FR-1",
            "time": "26.47",
            "meet_date": "Mar 14, 2025",
            "wind": "-0.1"
        },
        {
            "place": 7,
            "athlete": {
                "text": "Marsella, Bethany",
                "link": "https://www.tfrrs.org/athletes/8675809/Bryant/Bethany_Marsella"
            },
            "team": null,
            "year": "SO-2",
            "time": "27.54",
            "meet_date": "Apr 18, 2025",
            "wind": "0.2"
        },
        {
            "place": 8,
            "athlete": {
                "text": "Guadagnoli, Emma",
                "link": "https://www.tfrrs.org/athletes/8940136/Bryant/Emma_Guadagnoli"
            },
            "team": null,
            "year": "SO-2",
            "time": "27.80",
            "meet_date": "Apr 18, 2025",
            "wind": "0.2"
        },
        {
            "place": 9,
            "athlete": {
                "text": "Grzybinski, Emma",
                "link": "https://www.tfrrs.org/athletes/7926570/Bryant/Emma_Grzybinski"
            },
            "team": null,
            "year": "SR-4",
            "time": "28.94",
            "meet_date": "Apr 18, 2025",
            "wind": "-0.7"
        }
    ],
    "400m": [
        {
            "place": 1,
            "athlete": {
                "text": "Pineda, Savannah",
                "link": "https://www.tfrrs.org/athletes/7981526/Bryant/Savannah_Pineda"
            },
            "team": null,
            "year": "SR-4",
            "time": "54.92",
            "meet_date": "May 3, 2025",
            "wind": null
        },
        {
            "place": 2,
            "athlete": {
                "text": "Haddad, Lauren",
                "link": "https://www.tfrrs.org/athletes/8675807/Bryant/Lauren_Haddad"
            },
            "team": null,
            "year": "SO-2",
            "time": "57.28",
            "meet_date": "May 10, 2025",
            "wind": null
        },
        {
            "place": 3,
            "athlete": {
                "text": "Broussard, Amanda",
                "link": "https://www.tfrrs.org/athletes/8328693/Bryant/Amanda_Broussard"
            },
            "team": null,
            "year": "JR-3",
            "time": "58.15",
            "meet_date": "May 3, 2025",
            "wind": null
        },
        {
            "place": 4,
            "athlete": {
                "text": "De La Rosa, Tishany",
                "link": "https://www.tfrrs.org/athletes/8984287/Bryant/Tishany_De_La_Rosa"
            },
            "team": null,
            "year": "FR-1",
            "time": "58.44",
            "meet_date": "May 3, 2025",
            "wind": null
        },
        {
            "place": 5,
            "athlete": {
                "text": "MacElhiney, Kelley",
                "link": "https://www.tfrrs.org/athletes/8615874/Bryant/Kelley_MacElhiney"
            },
            "team": null,
            "year": "SO-2",
            "time": "1:02.09",
            "meet_date": "Mar 14, 2025",
            "wind": null
        },
        {
            "place": 6,
            "athlete": {
                "text": "Ondy, Kayla",
                "link": "https://www.tfrrs.org/athletes/8276692/Bryant/Kayla_Ondy"
            },
            "team": null,
            "year": "JR-3",
            "time": "1:03.40",
            "meet_date": "Mar 14, 2025",
            "wind": null
        },
        {
            "place": 7,
            "athlete": {
                "text": "Grzybinski, Emma",
                "link": "https://www.tfrrs.org/athletes/7926570/Bryant/Emma_Grzybinski"
            },
            "team": null,
            "year": "SR-4",
            "time": "1:03.65",
            "meet_date": "Mar 14, 2025",
            "wind": null
        },
        {
            "place": 8,
            "athlete": {
                "text": "Bettez, Mia",
                "link": "https://www.tfrrs.org/athletes/8940135/Bryant/Mia_Bettez"
            },
            "team": null,
            "year": "FR-1",
            "time": "1:05.11",
            "meet_date": "Apr 12, 2025",
            "wind": null
        },
        {
            "place": 9,
            "athlete": {
                "text": "Whiting, Chloe",
                "link": "https://www.tfrrs.org/athletes/7926572/Bryant/Chloe__Whiting"
            },
            "team": null,
            "year": "JR-3",
            "time": "1:05.79",
            "meet_date": "Mar 14, 2025",
            "wind": null
        },
        {
            "place": 10,
            "athlete": {
                "text": "Pachter, Liv",
                "link": "https://www.tfrrs.org/athletes/8940133/Bryant/Liv_Pachter"
            },
            "team": null,
            "year": "FR-1",
            "time": "1:06.00",
            "meet_date": "Apr 12, 2025",
            "wind": null
        }
    ],
    "800m": [
        {
            "place": 1,
            "athlete": {
                "text": "MacElhiney, Kelley",
                "link": "https://www.tfrrs.org/athletes/8615874/Bryant/Kelley_MacElhiney"
            },
            "team": null,
            "year": "SO-2",
            "time": "2:14.15",
            "meet_date": "May 3, 2025",
            "wind": null
        },
        {
            "place": 2,
            "athlete": {
                "text": "Guadagnoli, Emma",
                "link": "https://www.tfrrs.org/athletes/8940136/Bryant/Emma_Guadagnoli"
            },
            "team": null,
            "year": "SO-2",
            "time": "2:16.88",
            "meet_date": "Apr 18, 2025",
            "wind": null
        },
        {
            "place": 3,
            "athlete": {
                "text": "Grzybinski, Emma",
                "link": "https://www.tfrrs.org/athletes/7926570/Bryant/Emma_Grzybinski"
            },
            "team": null,
            "year": "SR-4",
            "time": "2:17.47",
            "meet_date": "Apr 18, 2025",
            "wind": null
        },
        {
            "place": 4,
            "athlete": {
                "text": "Ondy, Kayla",
                "link": "https://www.tfrrs.org/athletes/8276692/Bryant/Kayla_Ondy"
            },
            "team": null,
            "year": "JR-3",
            "time": "2:20.13",
            "meet_date": "Apr 25, 2025",
            "wind": null
        },
        {
            "place": 5,
            "athlete": {
                "text": "Bettez, Mia",
                "link": "https://www.tfrrs.org/athletes/8940135/Bryant/Mia_Bettez"
            },
            "team": null,
            "year": "FR-1",
            "time": "2:24.34",
            "meet_date": "May 3, 2025",
            "wind": null
        },
        {
            "place": 6,
            "athlete": {
                "text": "Pachter, Liv",
                "link": "https://www.tfrrs.org/athletes/8940133/Bryant/Liv_Pachter"
            },
            "team": null,
            "year": "FR-1",
            "time": "2:26.06",
            "meet_date": "Apr 25, 2025",
            "wind": null
        },
        {
            "place": 7,
            "athlete": {
                "text": "Kalinowski, Amanda",
                "link": "https://www.tfrrs.org/athletes/8984289/Bryant/Amanda_Kalinowski"
            },
            "team": null,
            "year": "FR-1",
            "time": "2:34.03",
            "meet_date": "Apr 9, 2025",
            "wind": null
        },
        {
            "place": 8,
            "athlete": {
                "text": "Spinelli, Adriana",
                "link": "https://www.tfrrs.org/athletes/8940134/Bryant/Adriana_Spinelli"
            },
            "team": null,
            "year": "FR-1",
            "time": "2:37.33",
            "meet_date": "Apr 25, 2025",
            "wind": null
        }
    ],
    "1500m": [
        {
            "place": 1,
            "athlete": {
                "text": "MacElhiney, Kelley",
                "link": "https://www.tfrrs.org/athletes/8615874/Bryant/Kelley_MacElhiney"
            },
            "team": null,
            "year": "SO-2",
            "time": "4:39.75",
            "meet_date": "Mar 28, 2025",
            "wind": null
        },
        {
            "place": 2,
            "athlete": {
                "text": "Grzybinski, Emma",
                "link": "https://www.tfrrs.org/athletes/7926570/Bryant/Emma_Grzybinski"
            },
            "team": null,
            "year": "SR-4",
            "time": "4:41.77",
            "meet_date": "May 10, 2025",
            "wind": null
        },
        {
            "place": 3,
            "athlete": {
                "text": "Berardino, Isabel",
                "link": "https://www.tfrrs.org/athletes/8615872/Bryant/Isabel_Berardino"
            },
            "team": null,
            "year": "SO-2",
            "time": "4:50.74",
            "meet_date": "Apr 25, 2025",
            "wind": null
        },
        {
            "place": 4,
            "athlete": {
                "text": "Pachter, Liv",
                "link": "https://www.tfrrs.org/athletes/8940133/Bryant/Liv_Pachter"
            },
            "team": null,
            "year": "FR-1",
            "time": "4:53.45",
            "meet_date": "May 3, 2025",
            "wind": null
        },
        {
            "place": 5,
            "athlete": {
                "text": "Ondy, Kayla",
                "link": "https://www.tfrrs.org/athletes/8276692/Bryant/Kayla_Ondy"
            },
            "team": null,
            "year": "JR-3",
            "time": "4:57.05",
            "meet_date": "Apr 18, 2025",
            "wind": null
        },
        {
            "place": 6,
            "athlete": {
                "text": "Nadolski, Emma",
                "link": "https://www.tfrrs.org/athletes/8615875/Bryant/Emma_Nadolski"
            },
            "team": null,
            "year": "SO-2",
            "time": "5:03.75",
            "meet_date": "Apr 12, 2025",
            "wind": null
        },
        {
            "place": 7,
            "athlete": {
                "text": "Bettez, Mia",
                "link": "https://www.tfrrs.org/athletes/8940135/Bryant/Mia_Bettez"
            },
            "team": null,
            "year": "FR-1",
            "time": "5:12.14",
            "meet_date": "Apr 18, 2025",
            "wind": null
        },
        {
            "place": 8,
            "athlete": {
                "text": "Puleo, Norah",
                "link": "https://www.tfrrs.org/athletes/8940132/Bryant/Norah_Puleo"
            },
            "team": null,
            "year": "FR-1",
            "time": "5:12.26",
            "meet_date": "Apr 3, 2025",
            "wind": null
        },
        {
            "place": 9,
            "athlete": {
                "text": "Pourmousa, Hanah",
                "link": "https://www.tfrrs.org/athletes/8615876/Bryant/Hanah_Pourmousa"
            },
            "team": null,
            "year": "SO-2",
            "time": "5:37.54",
            "meet_date": "Apr 3, 2025",
            "wind": null
        }
    ],
    "3000msc": [
        {
            "place": 1,
            "athlete": {
                "text": "Berardino, Isabel",
                "link": "https://www.tfrrs.org/athletes/8615872/Bryant/Isabel_Berardino"
            },
            "team": null,
            "year": "SO-2",
            "time": "11:11.59",
            "meet_date": "May 3, 2025",
            "wind": null
        },
        {
            "place": 2,
            "athlete": {
                "text": "Kamperides, Myah",
                "link": "https://www.tfrrs.org/athletes/8276690/Bryant/Myah_Kamperides"
            },
            "team": null,
            "year": "JR-3",
            "time": "12:04.47",
            "meet_date": "Apr 3, 2025",
            "wind": null
        },
        {
            "place": 3,
            "athlete": {
                "text": "Spinelli, Adriana",
                "link": "https://www.tfrrs.org/athletes/8940134/Bryant/Adriana_Spinelli"
            },
            "team": null,
            "year": "FR-1",
            "time": "13:49.21",
            "meet_date": "Apr 3, 2025",
            "wind": null
        }
    ],
    "5000m": [
        {
            "place": 1,
            "athlete": {
                "text": "Whiting, Chloe",
                "link": "https://www.tfrrs.org/athletes/7926572/Bryant/Chloe__Whiting"
            },
            "team": null,
            "year": "JR-3",
            "time": "15:51.38",
            "meet_date": "May 28, 2025",
            "wind": null
        },
        {
            "place": 2,
            "athlete": {
                "text": "Trott, Jasmine",
                "link": "https://www.tfrrs.org/athletes/8276694/Bryant/Jasmine_Trott"
            },
            "team": null,
            "year": "JR-3",
            "time": "16:16.54",
            "meet_date": "Apr 24, 2025",
            "wind": null
        },
        {
            "place": 3,
            "athlete": {
                "text": "Curran, Casey",
                "link": "https://www.tfrrs.org/athletes/8276689/Bryant/Casey_Curran"
            },
            "team": null,
            "year": "JR-3",
            "time": "17:06.18",
            "meet_date": "May 3, 2025",
            "wind": null
        },
        {
            "place": 4,
            "athlete": {
                "text": "Fisher, Alexa",
                "link": "https://www.tfrrs.org/athletes/8615873/Bryant/Alexa_Fisher"
            },
            "team": null,
            "year": "SO-2",
            "time": "18:26.49",
            "meet_date": "May 3, 2025",
            "wind": null
        },
        {
            "place": 5,
            "athlete": {
                "text": "Puleo, Norah",
                "link": "https://www.tfrrs.org/athletes/8940132/Bryant/Norah_Puleo"
            },
            "team": null,
            "year": "FR-1",
            "time": "19:04.71",
            "meet_date": "May 3, 2025",
            "wind": null
        },
        {
            "place": 6,
            "athlete": {
                "text": "Nadolski, Emma",
                "link": "https://www.tfrrs.org/athletes/8615875/Bryant/Emma_Nadolski"
            },
            "team": null,
            "year": "SO-2",
            "time": "19:16.91",
            "meet_date": "Apr 3, 2025",
            "wind": null
        },
        {
            "place": 7,
            "athlete": {
                "text": "Pourmousa, Hanah",
                "link": "https://www.tfrrs.org/athletes/8615876/Bryant/Hanah_Pourmousa"
            },
            "team": null,
            "year": "SO-2",
            "time": "20:53.41",
            "meet_date": "Apr 25, 2025",
            "wind": null
        }
    ],
    "10000m": [
        {
            "place": 1,
            "athlete": {
                "text": "Trott, Jasmine",
                "link": "https://www.tfrrs.org/athletes/8276694/Bryant/Jasmine_Trott"
            },
            "team": null,
            "year": "JR-3",
            "time": "33:35.17",
            "meet_date": "Apr 16, 2025",
            "wind": null
        },
        {
            "place": 2,
            "athlete": {
                "text": "Whiting, Chloe",
                "link": "https://www.tfrrs.org/athletes/7926572/Bryant/Chloe__Whiting"
            },
            "team": null,
            "year": "JR-3",
            "time": "36:44.91",
            "meet_date": "May 3, 2025",
            "wind": null
        },
        {
            "place": 3,
            "athlete": {
                "text": "Curran, Casey",
                "link": "https://www.tfrrs.org/athletes/8276689/Bryant/Casey_Curran"
            },
            "team": null,
            "year": "JR-3",
            "time": "37:03.44",
            "meet_date": "May 3, 2025",
            "wind": null
        },
        {
            "place": 4,
            "athlete": {
                "text": "Fisher, Alexa",
                "link": "https://www.tfrrs.org/athletes/8615873/Bryant/Alexa_Fisher"
            },
            "team": null,
            "year": "SO-2",
            "time": "39:07.76",
            "meet_date": "May 10, 2025",
            "wind": null
        }
    ],
    "100mh": [
        {
            "place": 1,
            "athlete": {
                "text": "Marsella, Bethany",
                "link": "https://www.tfrrs.org/athletes/8675809/Bryant/Bethany_Marsella"
            },
            "team": null,
            "year": "SO-2",
            "time": "15.08",
            "meet_date": "May 3, 2025",
            "wind": "1.3"
        },
        {
            "place": 2,
            "athlete": {
                "text": "Style, Caitlin",
                "link": "https://www.tfrrs.org/athletes/8984293/Bryant/Caitlin_Style"
            },
            "team": null,
            "year": "FR-1",
            "time": "15.09",
            "meet_date": "May 10, 2025",
            "wind": "5.1"
        },
        {
            "place": 3,
            "athlete": {
                "text": "Fodera, Maggie",
                "link": "https://www.tfrrs.org/athletes/7981522/Bryant/Maggie_Fodera"
            },
            "team": null,
            "year": "SR-4",
            "time": "15.80",
            "meet_date": "Mar 28, 2025",
            "wind": "0.9"
        },
        {
            "place": 4,
            "athlete": {
                "text": "Kalinowski, Amanda",
                "link": "https://www.tfrrs.org/athletes/8984289/Bryant/Amanda_Kalinowski"
            },
            "team": null,
            "year": "FR-1",
            "time": "16.09",
            "meet_date": "May 3, 2025",
            "wind": "-1.0"
        }
    ],
    "400mh": [
        {
            "place": 1,
            "athlete": {
                "text": "Kalinowski, Amanda",
                "link": "https://www.tfrrs.org/athletes/8984289/Bryant/Amanda_Kalinowski"
            },
            "team": null,
            "year": "FR-1",
            "time": "1:07.92",
            "meet_date": "Mar 28, 2025",
            "wind": null
        },
        {
            "place": 2,
            "athlete": {
                "text": "Berardino, Isabel",
                "link": "https://www.tfrrs.org/athletes/8615872/Bryant/Isabel_Berardino"
            },
            "team": null,
            "year": "SO-2",
            "time": "1:12.14",
            "meet_date": "Apr 3, 2025",
            "wind": null
        },
        {
            "place": 3,
            "athlete": {
                "text": "Kamperides, Myah",
                "link": "https://www.tfrrs.org/athletes/8276690/Bryant/Myah_Kamperides"
            },
            "team": null,
            "year": "JR-3",
            "time": "1:21.56",
            "meet_date": "Apr 3, 2025",
            "wind": null
        }
    ]
}